{"file":"shezhisheet.png","frames":{
"zhaoxiangji":{"x":854,"y":740,"w":54,"h":54,"offX":62,"offY":62,"sourceW":120,"sourceH":120},
"xuanzhongtouxiang":{"x":752,"y":202,"w":136,"h":136,"offX":0,"offY":0,"sourceW":136,"sourceH":136},
"xiugai":{"x":996,"y":458,"w":24,"h":24,"offX":0,"offY":0,"sourceW":24,"sourceH":24},
"txkuang":{"x":752,"y":340,"w":120,"h":120,"offX":0,"offY":0,"sourceW":120,"sourceH":120},
"touxiangkuang":{"x":890,"y":334,"w":122,"h":122,"offX":0,"offY":0,"sourceW":122,"sourceH":122},
"on":{"x":752,"y":580,"w":145,"h":70,"offX":7,"offY":0,"sourceW":154,"sourceH":70},
"off":{"x":752,"y":652,"w":145,"h":70,"offX":2,"offY":0,"sourceW":154,"sourceH":70},
"linshitouxiang":{"x":890,"y":202,"w":130,"h":130,"offX":0,"offY":0,"sourceW":130,"sourceH":130},
"headkuang":{"x":874,"y":458,"w":120,"h":120,"offX":0,"offY":0,"sourceW":120,"sourceH":120},
"guanbi01":{"x":899,"y":580,"w":78,"h":78,"offX":0,"offY":0,"sourceW":78,"sourceH":78},
"guanbi00":{"x":899,"y":660,"w":78,"h":78,"offX":0,"offY":0,"sourceW":78,"sourceH":78},
"gonggaokuang":{"x":0,"y":1576,"w":718,"h":34,"offX":0,"offY":0,"sourceW":718,"sourceH":34},
"fengexian":{"x":1007,"y":0,"w":2,"h":100,"offX":0,"offY":0,"sourceW":2,"sourceH":100},
"bankuai":{"x":0,"y":1336,"w":420,"h":156,"offX":0,"offY":0,"sourceW":420,"sourceH":156},
"anniu01":{"x":752,"y":101,"w":253,"h":99,"offX":1,"offY":1,"sourceW":254,"sourceH":100},
"anniu00":{"x":752,"y":0,"w":253,"h":99,"offX":1,"offY":1,"sourceW":254,"sourceH":100},
"sxflan":{"x":0,"y":1494,"w":750,"h":80,"offX":0,"offY":0,"sourceW":750,"sourceH":80},
"bj":{"x":0,"y":0,"w":750,"h":1334,"offX":0,"offY":0,"sourceW":750,"sourceH":1334},
"di":{"x":910,"y":740,"w":50,"h":52,"offX":0,"offY":0,"sourceW":50,"sourceH":52},
"fangge":{"x":752,"y":462,"w":100,"h":100,"offX":0,"offY":0,"sourceW":100,"sourceH":100},
"lan":{"x":752,"y":724,"w":100,"h":52,"offX":0,"offY":0,"sourceW":100,"sourceH":52},
"line":{"x":1011,"y":0,"w":10,"h":2,"offX":0,"offY":0,"sourceW":10,"sourceH":2}}}